alchemical_queues/__init__.py
alchemical_queues/main.py
alchemical_queues/py.typed
alchemical_queues/tasks/__init__.py
alchemical_queues/tasks/cli.py
alchemical_queues/tasks/main.py
alchemical_queues/tasks/py.typed
alchemical_queues-0.1.1.dist-info/METADATA
alchemical_queues-0.1.1.dist-info/WHEEL
alchemical_queues-0.1.1.dist-info/entry_points.txt
alchemical_queues-0.1.1.dist-info/LICENSE.md
alchemical_queues-0.1.1.dist-info/RECORD
