Metadata-Version: 2.1
Name: alchemical-queues
Version: 0.1.1
Summary: Task Queues on pure SQLAlchemy
License: MIT
Author: Thijs Miedema
Author-email: mail@tmiedema.com
Requires-Python: >=3.7
Classifier: License :: OSI Approved :: MIT License
Classifier: Programming Language :: Python :: 3
Classifier: Programming Language :: Python :: 3.7
Classifier: Programming Language :: Python :: 3.8
Classifier: Programming Language :: Python :: 3.9
Classifier: Programming Language :: Python :: 3.10
Classifier: Programming Language :: Python :: 3.11
Requires-Dist: SQLAlchemy (>=1,<2)
Requires-Dist: typing_extensions
